csvw_duckdb/__init__.py
csvw_duckdb/__main__.py
csvw_duckdb/table.py
csvw_duckdb/table_group.py
csvw_duckdb-0.0.1.dist-info/LICENSE
csvw_duckdb-0.0.1.dist-info/METADATA
csvw_duckdb-0.0.1.dist-info/WHEEL
csvw_duckdb-0.0.1.dist-info/entry_points.txt
csvw_duckdb-0.0.1.dist-info/top_level.txt
csvw_duckdb-0.0.1.dist-info/RECORD
