Metadata-Version: 2.1
Name: csvw-duckdb
Version: 0.0.1
Summary: Convert CSVW metadata to DuckDB SQL syntax.
Project-URL: Homepage, https://pypi.org/p/csvw-duckdb
Project-URL: Repository, https://github.com/CUREd-Plus/csvw-duckdb
Project-URL: Issues, https://github.com/CUREd-Plus/csvw-duckdb/issues
Project-URL: Changelog, https://github.com/CUREd-Plus/csvw-duckdb/releases
Classifier: Programming Language :: Python :: 3
Classifier: License :: OSI Approved :: MIT License
Classifier: Operating System :: OS Independent
License-File: LICENSE
Requires-Dist: csvw==3.*
Requires-Dist: duckdb==1.*
